{
   "Scripts":[
      {
         "scriptId":1,
         "scriptName":"Weather",
         "isDefault":0,
         "ScriptText":[
            {
               "scriptTextId":1,
               "sequence":0,
               "theText":"Text a ZIP code",
               "responseParser":{
                  "responseType":"text",
                  "responses":[
                     {
                        "response":"",
                        "reply":"",
                        "goto":"1",
                        "scriptId":null,
                        "attribute":"zip"
                     }
                  ],
                  "error":{
                     "reply":"",
                     "goto":"1",
                     "attribute":"zip"
                  }
               },
               "videoGuid":null,
               "emailAfterSend":0,
               "Reminder":0,
               "reminderMsg":null,
               "emailSubject":null,
               "webhook":null,
               "statusIdAfterSend":null
            },
            {
               "scriptTextId":2,
               "sequence":1,
               "theText":"",
               "responseParser":{
                  "responseType":"text",
                  "responses":[
                     {
                        "response":"",
                        "reply":"",
                        "goto":1,
                        "scriptId":null,
                        "attribute":"zip"
                     }
                  ],
                  "response":null,
                  "error":{
                     "response":"",
                     "reply":"",
                     "goto":"1",
                     "attribute":"zip"
                  },
                  "yes":null,
                  "no":null
               },
               "videoGuid":null,
               "emailAfterSend":0,
               "Reminder":0,
               "reminderMsg":null,
               "emailSubject":null,
               "webhook":"https:\/\/yourbackend.com\/weather.php",
               "statusIdAfterSend":null
            }
         ]
      }
   ],
   "TemplateVariables":[
   ],
   "Statuses":[
   ]
}
